setup.py
django_db_cascade/__init__.py
django_db_cascade/deletions.py
django_db_cascade/fields.py
django_db_cascade.egg-info/PKG-INFO
django_db_cascade.egg-info/SOURCES.txt
django_db_cascade.egg-info/dependency_links.txt
django_db_cascade.egg-info/not-zip-safe
django_db_cascade.egg-info/requires.txt
django_db_cascade.egg-info/top_level.txt
django_db_cascade/backends/__init__.py
django_db_cascade/backends/postgresql_psycopg2/__init__.py
django_db_cascade/backends/postgresql_psycopg2/base.py
django_db_cascade/backends/postgresql_psycopg2/schema.py