Metadata-Version: 1.1
Name: django-db-cascade
Version: 0.1.6
Summary: Optionally use postgres db ON CASCADE DELETE on django foreign keys
Home-page: http://github.com/nickstefan/django-db-cascade
Author: Nick Stefan
Author-email: nickstefan12@gmail.com
License: MIT
Platform: UNKNOWN
Classifier: Framework :: Django
Classifier: Topic :: Database
